langdict/__init__.py
langdict/langdict.py
langdict/builders/__init__.py
langdict/builders/base.py
langdict/builders/chat_prompt.py
langdict/builders/lite_llm.py
langdict/builders/output_parser.py
langdict/builders/text_prompt.py
langdict/builders/trace.py
langdict/chat_models/__init__.py
langdict/chat_models/litellm.py
langdict/modules/__init__.py
langdict/modules/langdict_module.py
langdict/modules/module.py
langdict/modules/parameter.py
langdict/specs/__init__.py
langdict/specs/base.py
langdict/specs/lang.py
langdict/specs/llm.py
langdict/specs/output.py
langdict/specs/prompt.py
langdict/traces/__init__.py
langdict/traces/backend.py
langdict/traces/callbacks/__init__.py
langdict/traces/callbacks/stdout.py
langdict-0.0.2.dist-info/LICENSE
langdict-0.0.2.dist-info/METADATA
langdict-0.0.2.dist-info/WHEEL
langdict-0.0.2.dist-info/top_level.txt
langdict-0.0.2.dist-info/RECORD
