Metadata-Version: 2.1
Name: langdict
Version: 0.0.2
Summary: Build complex LLM Applications with Python Dictionary
Author-email: Dongjun Lee <djlee.hb@gmail.com>
Maintainer-email: Dongjun Lee <djlee.hb@gmail.com>
License: MIT License
Project-URL: Homepage, https://langdict.github.io/
Project-URL: Documentation, https://langdict.github.io/docs
Project-URL: Repository, https://github.com/LangDict/langdict.git
Project-URL: Bug Tracker, https://github.com/LangDict/langdict/issues
Keywords: LLM,RAG,Agent,Compund AI Systems,LangDict
Classifier: Development Status :: 3 - Alpha
Classifier: Intended Audience :: Developers
Classifier: Topic :: Software Development :: Libraries :: Python Modules
Classifier: License :: OSI Approved :: MIT License
Classifier: Programming Language :: Python :: 3
Classifier: Programming Language :: Python :: 3.9
Classifier: Programming Language :: Python :: 3.10
Classifier: Programming Language :: Python :: 3.11
Classifier: Programming Language :: Python :: 3.12
Classifier: Programming Language :: Python :: 3 :: Only
Requires-Python: <4.0,>=3.9
License-File: LICENSE
Provides-Extra: dev
Provides-Extra: test
Requires-Dist: pytest; extra == "test"
